structpy/__init__.py
structpy/parser.py
structpy/automaton/__init__.py
structpy/automaton/dfa.py
structpy/automaton/state_machine.py
structpy/collection/__init__.py
structpy/collection/bidictionary.py
structpy/collection/default_dictionary.py
structpy/collection/multibidict.py
structpy/collection/test/__init__.py
structpy/collection/test/test_bidictionary.py
structpy/collection/test/test_default_dictionary.py
structpy/collection/test/test_multibidictionary.py
structpy/graph/__init__.py
structpy/graph/database.py
structpy/graph/element.py
structpy/graph/digraph/__init__.py
structpy/graph/digraph/digraph.py
structpy/graph/digraph/ordered_bidigraph.py
structpy/graph/labeled_digraph/__init__.py
structpy/graph/labeled_digraph/deteministic_map_digraph.py
structpy/graph/labeled_digraph/labeled_digraph.py
structpy/graph/labeled_digraph/labeled_ordered_digraph.py
structpy/graph/labeled_digraph/map_digraph.py
structpy/graph/labeled_digraph/map_multidigraph.py
structpy/graph/labeled_digraph/source_map_digraph.py
structpy/graph/labeled_digraph/test_labeled_digraph.py
structpy/graph/labeled_graph/__init__.py
structpy/graph/labeled_graph/labeled_graph_base.py
structpy/graph/labeled_graph_tree/__init__.py
structpy/graph/labeled_graph_tree/labeled_graph_tree.py
structpy/graph/labeled_graph_tree/test_labeled_graph_tree.py
structpy/graph/map_graph/__init__.py
structpy/graph/map_graph/map_graph.py
structpy/graph/net/__init__.py
structpy/graph/net/net.py
structpy/graph/net/net_node.py
structpy/graph/net/network.py
structpy/graph/net/network_node.py
structpy/graph/net/test_node_net.py
structpy/graph/net/test_node_network.py
structpy/graph/traversal/__init__.py
structpy/graph/traversal/preset.py
structpy/graph/traversal/rings.py
structpy/graph/traversal/traversal.py
structpy/graph/traversal/traversal_step.py
structpy/graph/traversal/frontier/__init__.py
structpy/graph/traversal/frontier/frontier.py
structpy/graph/traversal/frontier/queue.py
structpy/graph/traversal/frontier/stack.py
structpy-0.3.dist-info/METADATA
structpy-0.3.dist-info/WHEEL
structpy-0.3.dist-info/top_level.txt
structpy-0.3.dist-info/RECORD
