Metadata-Version: 2.1
Name: structpy
Version: 0.3
Summary: Graph algorithms and data structures
Home-page: https://github.com/jdfinch/structpy
Author: James Finch
Author-email: jdfinch@emory.edu
License: UNKNOWN
Platform: UNKNOWN
Classifier: Programming Language :: Python :: 3
Classifier: License :: OSI Approved :: MIT License
Classifier: Operating System :: OS Independent
